TMotorCANControl/__init__.py
TMotorCANControl/mit_can.py
TMotorCANControl/servo_can.py
TMotorCANControl/servo_serial.py
TMotorCANControl-1.2.6.dist-info/METADATA
TMotorCANControl-1.2.6.dist-info/WHEEL
TMotorCANControl-1.2.6.dist-info/top_level.txt
TMotorCANControl-1.2.6.dist-info/RECORD
